README.rst
setup.py
SmartRPyC.egg-info/PKG-INFO
SmartRPyC.egg-info/SOURCES.txt
SmartRPyC.egg-info/dependency_links.txt
SmartRPyC.egg-info/requires.txt
SmartRPyC.egg-info/top_level.txt
smartrpyc/__init__.py
smartrpyc/exceptions.py
smartrpyc/utils.py
smartrpyc/client/__init__.py
smartrpyc/client/base.py
smartrpyc/client/exceptions.py
smartrpyc/client/pirate.py
smartrpyc/contrib/__init__.py
smartrpyc/contrib/public/__init__.py
smartrpyc/contrib/public/client.py
smartrpyc/contrib/public/server.py
smartrpyc/server/__init__.py
smartrpyc/server/base.py
smartrpyc/tests/__init__.py
smartrpyc/tests/utils.py
smartrpyc/tests/functional/__init__.py
smartrpyc/tests/functional/test_lazy.py
smartrpyc/tests/functional/test_smartrpc.py
smartrpyc/tests/unit/__init__.py
smartrpyc/tests/unit/test_methods.py