Metadata-Version: 1.1
Name: SmartRPyC
Version: 0.1-beta2
Summary: SmartRPyC is a ZeroMQ-based RPC library for Python
Home-page: UNKNOWN
Author: Samuele Santi - Flavio Percoco
Author-email: samuele@samuelesanti.com - flaper87@flaper87.org
License: Apache License, Version 2.0, January 2004
Platform: UNKNOWN
Classifier: License :: OSI Approved :: Apache Software License
Classifier: Development Status :: 4 - Beta
Classifier: Topic :: Software Development :: Libraries
Classifier: Topic :: System :: Networking
